<song>
    <general>
        <name>晴天</name>
        <singer>周杰伦</singer>
        <type>1</type>
    </general>
    <midi_lrc>
        <paragraph>
            <sentence>
                <tone begin="32.502" end="32.756" lang="1" pitch="284" pronounce="">
                    <word>故</word>
                </tone>
                <tone begin="32.756" end="33.21" lang="1" pitch="248" pronounce="">
                    <word>事</word>
                </tone>
                <tone begin="33.21" end="33.616" lang="1" pitch="193" pronounce="">
                    <word>的</word>
                </tone>
                <tone begin="33.616" end="34.577" lang="1" pitch="194" pronounce="">
                    <word>小</word>
                </tone>
                <tone begin="34.577" end="35.083" lang="1" pitch="220" pronounce="">
                    <word>黄</word>
                </tone>
                <tone begin="35.083" end="35.385" lang="1" pitch="246" pronounce="">
                    <word>花</word>
                </tone>
            </sentence>
            <sentence>
                <tone begin="35.891" end="36.297" lang="1" pitch="285" pronounce="">
                    <word>从</word>
                </tone>
                <tone begin="36.297" end="36.754" lang="1" pitch="317" pronounce="">
                    <word>出</word>
                </tone>
                <tone begin="36.754" end="37.158" lang="1" pitch="196" pronounce="">
                    <word>生</word>
                </tone>
                <tone begin="37.158" end="37.615" lang="1" pitch="195" pronounce="">
                    <word>那</word>
                </tone>
                <tone begin="37.615" end="38.018" lang="1" pitch="223" pronounce="">
                    <word>年</word>
                </tone>
                <tone begin="38.018" end="38.171" lang="1" pitch="224" pronounce="">
                    <word>就</word>
                </tone>
                <tone begin="38.171" end="38.525" lang="1" pitch="195" pronounce="">
                    <word>飘</word>
                </tone>
                <tone begin="38.525" end="38.879" lang="1" pitch="143" pronounce="">
                    <word>着</word>
                </tone>
            </sentence>
            <sentence>
                <tone begin="39.386" end="39.791" lang="1" pitch="284" pronounce="">
                    <word>童</word>
                </tone>
                <tone begin="39.791" end="40.194" lang="1" pitch="265" pronounce="">
                    <word>年</word>
                </tone>
                <tone begin="40.194" end="40.699" lang="1" pitch="193" pronounce="">
                    <word>的</word>
                </tone>
                <tone begin="40.699" end="41.511" lang="1" pitch="194" pronounce="">
                    <word>荡</word>
                </tone>
                <tone begin="41.511" end="42.119" lang="1" pitch="228" pronounce="">
                    <word>秋</word>
                </tone>
                <tone begin="42.119" end="42.424" lang="1" pitch="244" pronounce="">
                    <word>千</word>
                </tone>
            </sentence>
            <sentence>
                <tone begin="42.935" end="43.289" lang="1" pitch="238" pronounce="">
                    <word>随</word>
                </tone>
                <tone begin="43.795" end="44.15" lang="1" pitch="205" pronounce="">
                    <word>记</word>
                </tone>
                <tone begin="44.15" end="44.557" lang="1" pitch="249" pronounce="">
                    <word>忆</word>
                </tone>
                <tone begin="44.557" end="44.709" lang="1" pitch="232" pronounce="">
                    <word>一</word>
                </tone>
                <tone begin="44.709" end="44.861" lang="1" pitch="221" pronounce="">
                    <word>直</word>
                </tone>
                <tone begin="44.861" end="45.011" lang="1" pitch="254" pronounce="">
                    <word>晃</word>
                </tone>
                <tone begin="45.011" end="45.214" lang="1" pitch="251" pronounce="">
                    <word>到</word>
                </tone>
                <tone begin="45.214" end="45.52" lang="1" pitch="223" pronounce="">
                    <word>现</word>
                </tone>
                <tone begin="45.52" end="45.721" lang="1" pitch="192" pronounce="">
                    <word>在</word>
                </tone>
            </sentence>
            <sentence>
                <tone begin="46.076" end="46.431" lang="1" pitch="168" pronounce="">
                    <word>e</word>
                </tone>
                <tone begin="46.431" end="46.735" lang="1" pitch="195" pronounce="">
                    <word>o</word>
                </tone>
                <tone begin="46.735" end="47.191" lang="1" pitch="194" pronounce="">
                    <word>o</word>
                </tone>
                <tone begin="47.191" end="47.645" lang="1" pitch="246" pronounce="">
                    <word>i</word>
                </tone>
                <tone begin="47.645" end="48.051" lang="1" pitch="250" pronounce="">
                    <word>o</word>
                </tone>
                <tone begin="48.051" end="48.558" lang="1" pitch="237" pronounce="">
                    <word>i</word>
                </tone>
                <tone begin="48.558" end="48.762" lang="1" pitch="220" pronounce="">
                    <word>a</word>
                </tone>
            </sentence>
            <sentence>
                <tone begin="49.015" end="49.218" lang="1" pitch="195" pronounce="">
                    <word>o</word>
                </tone>
                <tone begin="49.218" end="49.369" lang="1" pitch="215" pronounce="">
                    <word>a</word>
                </tone>
                <tone begin="49.369" end="49.823" lang="1" pitch="233" pronounce="">
                    <word>i</word>
                </tone>
                <tone begin="49.823" end="50.23" lang="1" pitch="243" pronounce="">
                    <word>i</word>
                </tone>
                <tone begin="50.23" end="50.735" lang="1" pitch="276" pronounce="">
                    <word>i</word>
                </tone>
                <tone begin="50.735" end="51.242" lang="1" pitch="236" pronounce="">
                    <word>i</word>
                </tone>
                <tone begin="51.242" end="51.444" lang="1" pitch="220" pronounce="">
                    <word>a</word>
                </tone>
                <tone begin="51.444" end="51.646" lang="1" pitch="242" pronounce="">
                    <word>i</word>
                </tone>
                <tone begin="51.646" end="52.102" lang="1" pitch="214" pronounce="">
                    <word>a</word>
                </tone>
                <tone begin="52.102" end="52.306" lang="1" pitch="193" pronounce="">
                    <word>o</word>
                </tone>
            </sentence>
            <sentence>
                <tone begin="52.948" end="53.354" lang="1" pitch="146" pronounce="">
                    <word>吹</word>
                </tone>
                <tone begin="53.354" end="53.758" lang="1" pitch="187" pronounce="">
                    <word>着</word>
                </tone>
                <tone begin="53.758" end="54.213" lang="1" pitch="202" pronounce="">
                    <word>前</word>
                </tone>
                <tone begin="54.213" end="54.672" lang="1" pitch="241" pronounce="">
                    <word>奏</word>
                </tone>
                <tone begin="54.672" end="55.13" lang="1" pitch="253" pronounce="">
                    <word>望</word>
                </tone>
                <tone begin="55.13" end="55.535" lang="1" pitch="236" pronounce="">
                    <word>着</word>
                </tone>
                <tone begin="55.535" end="55.99" lang="1" pitch="229" pronounce="">
                    <word>天</word>
                </tone>
                <tone begin="55.99" end="56.19" lang="1" pitch="202" pronounce="">
                    <word>空</word>
                </tone>
            </sentence>
            <sentence>
                <tone begin="56.394" end="56.596" lang="1" pitch="229" pronounce="">
                    <word>我</word>
                </tone>
                <tone begin="56.596" end="56.897" lang="1" pitch="244" pronounce="">
                    <word>想</word>
                </tone>
                <tone begin="56.897" end="57.302" lang="1" pitch="245" pronounce="">
                    <word>起</word>
                </tone>
                <tone begin="57.302" end="57.708" lang="1" pitch="234" pronounce="">
                    <word>花</word>
                </tone>
                <tone begin="57.708" end="58.215" lang="1" pitch="243" pronounce="">
                    <word>瓣</word>
                </tone>
                <tone begin="58.215" end="58.416" lang="1" pitch="227" pronounce="">
                    <word>试</word>
                </tone>
                <tone begin="58.416" end="58.619" lang="1" pitch="244" pronounce="">
                    <word>着</word>
                </tone>
                <tone begin="58.619" end="59.127" lang="1" pitch="213" pronounce="">
                    <word>掉</word>
                </tone>
                <tone begin="59.127" end="59.53" lang="1" pitch="192" pronounce="">
                    <word>落</word>
                </tone>
            </sentence>
            <sentence>
                <tone begin="59.935" end="60.086" lang="1" pitch="191" pronounce="">
                    <word>为</word>
                </tone>
                <tone begin="60.086" end="60.239" lang="1" pitch="197" pronounce="">
                    <word>你</word>
                </tone>
                <tone begin="60.239" end="60.443" lang="1" pitch="194" pronounce="">
                    <word>翘</word>
                </tone>
                <tone begin="60.443" end="60.646" lang="1" pitch="195" pronounce="">
                    <word>课</word>
                </tone>
                <tone begin="60.646" end="60.849" lang="1" pitch="193" pronounce="">
                    <word>的</word>
                </tone>
                <tone begin="60.849" end="61.101" lang="1" pitch="188" pronounce="">
                    <word>那</word>
                </tone>
                <tone begin="61.101" end="61.506" lang="1" pitch="193" pronounce="">
                    <word>一</word>
                </tone>
                <tone begin="61.506" end="61.657" lang="1" pitch="192" pronounce="">
                    <word>天</word>
                </tone>
            </sentence>
            <sentence>
                <tone begin="62.024" end="62.226" lang="1" pitch="192" pronounce="">
                    <word>花</word>
                </tone>
                <tone begin="62.226" end="62.477" lang="1" pitch="193" pronounce="">
                    <word>落</word>
                </tone>
                <tone begin="62.477" end="62.578" lang="1" pitch="190" pronounce="">
                    <word>的</word>
                </tone>
                <tone begin="62.578" end="62.882" lang="1" pitch="188" pronounce="">
                    <word>那</word>
                </tone>
                <tone begin="62.882" end="63.287" lang="1" pitch="197" pronounce="">
                    <word>一</word>
                </tone>
                <tone begin="63.287" end="63.438" lang="1" pitch="195" pronounce="">
                    <word>天</word>
                </tone>
            </sentence>
            <sentence>
                <tone begin="63.693" end="63.897" lang="1" pitch="269" pronounce="">
                    <word>教</word>
                </tone>
                <tone begin="63.897" end="64.1" lang="1" pitch="197" pronounce="">
                    <word>室</word>
                </tone>
                <tone begin="64.1" end="64.302" lang="1" pitch="193" pronounce="">
                    <word>的</word>
                </tone>
                <tone begin="64.302" end="64.605" lang="1" pitch="186" pronounce="">
                    <word>那</word>
                </tone>
                <tone begin="64.605" end="65.01" lang="1" pitch="192" pronounce="">
                    <word>一</word>
                </tone>
                <tone begin="65.01" end="65.163" lang="1" pitch="193" pronounce="">
                    <word>间</word>
                </tone>
            </sentence>
            <sentence>
                <tone begin="65.366" end="65.568" lang="1" pitch="194" pronounce="">
                    <word>我</word>
                </tone>
                <tone begin="65.568" end="65.77" lang="1" pitch="194" pronounce="">
                    <word>怎</word>
                </tone>
                <tone begin="65.77" end="65.973" lang="1" pitch="192" pronounce="">
                    <word>么</word>
                </tone>
                <tone begin="65.973" end="66.327" lang="1" pitch="250" pronounce="">
                    <word>看</word>
                </tone>
                <tone begin="66.327" end="66.733" lang="1" pitch="294" pronounce="">
                    <word>不</word>
                </tone>
                <tone begin="66.733" end="66.887" lang="1" pitch="298" pronounce="">
                    <word>见</word>
                </tone>
            </sentence>
            <sentence>
                <tone begin="67.143" end="67.395" lang="1" pitch="496" pronounce="">
                    <word>消</word>
                </tone>
                <tone begin="67.395" end="67.599" lang="1" pitch="287" pronounce="">
                    <word>失</word>
                </tone>
                <tone begin="67.599" end="67.801" lang="1" pitch="291" pronounce="">
                    <word>的</word>
                </tone>
                <tone begin="67.801" end="68.156" lang="1" pitch="294" pronounce="">
                    <word>下</word>
                </tone>
                <tone begin="68.156" end="68.561" lang="1" pitch="293" pronounce="">
                    <word>雨</word>
                </tone>
                <tone begin="68.561" end="68.763" lang="1" pitch="293" pronounce="">
                    <word>天</word>
                </tone>
            </sentence>
            <sentence>
                <tone begin="68.966" end="69.168" lang="1" pitch="295" pronounce="">
                    <word>我</word>
                </tone>
                <tone begin="69.168" end="69.37" lang="1" pitch="290" pronounce="">
                    <word>好</word>
                </tone>
                <tone begin="69.37" end="69.624" lang="1" pitch="291" pronounce="">
                    <word>想</word>
                </tone>
                <tone begin="69.624" end="69.876" lang="1" pitch="280" pronounce="">
                    <word>再</word>
                </tone>
                <tone begin="69.876" end="70.079" lang="1" pitch="259" pronounce="">
                    <word>淋</word>
                </tone>
                <tone begin="70.079" end="70.332" lang="1" pitch="236" pronounce="">
                    <word>一</word>
                </tone>
                <tone begin="70.332" end="71.041" lang="1" pitch="240" pronounce="">
                    <word>遍</word>
                </tone>
            </sentence>
            <sentence>
                <tone begin="73.149" end="73.404" lang="1" pitch="196" pronounce="">
                    <word>没</word>
                </tone>
                <tone begin="73.404" end="73.605" lang="1" pitch="188" pronounce="">
                    <word>想</word>
                </tone>
                <tone begin="73.605" end="73.808" lang="1" pitch="188" pronounce="">
                    <word>到</word>
                </tone>
                <tone begin="73.808" end="74.01" lang="1" pitch="193" pronounce="">
                    <word>失</word>
                </tone>
                <tone begin="74.01" end="74.364" lang="1" pitch="158" pronounce="">
                    <word>去</word>
                </tone>
                <tone begin="74.364" end="74.82" lang="1" pitch="181" pronounce="">
                    <word>的</word>
                </tone>
                <tone begin="74.82" end="75.224" lang="1" pitch="195" pronounce="">
                    <word>勇</word>
                </tone>
                <tone begin="75.224" end="75.73" lang="1" pitch="277" pronounce="">
                    <word>气</word>
                </tone>
                <tone begin="75.73" end="76.185" lang="1" pitch="274" pronounce="">
                    <word>我</word>
                </tone>
                <tone begin="76.185" end="76.64" lang="1" pitch="235" pronounce="">
                    <word>还</word>
                </tone>
                <tone begin="76.64" end="77.095" lang="1" pitch="194" pronounce="">
                    <word>留</word>
                </tone>
                <tone begin="77.095" end="77.904" lang="1" pitch="193" pronounce="">
                    <word>着</word>
                </tone>
            </sentence>
            <sentence>
                <tone begin="79.229" end="79.431" lang="1" pitch="196" pronounce="">
                    <word>好</word>
                </tone>
                <tone begin="79.431" end="79.634" lang="1" pitch="197" pronounce="">
                    <word>想</word>
                </tone>
                <tone begin="79.634" end="79.887" lang="1" pitch="194" pronounce="">
                    <word>再</word>
                </tone>
                <tone begin="79.887" end="80.14" lang="1" pitch="196" pronounce="">
                    <word>问</word>
                </tone>
                <tone begin="80.14" end="80.595" lang="1" pitch="219" pronounce="">
                    <word>一</word>
                </tone>
                <tone begin="80.595" end="80.697" lang="1" pitch="196" pronounce="">
                    <word>遍</word>
                </tone>
            </sentence>
            <sentence>
                <tone begin="80.95" end="81.406" lang="1" pitch="160" pronounce="">
                    <word>你</word>
                </tone>
                <tone begin="81.406" end="81.811" lang="1" pitch="179" pronounce="">
                    <word>会</word>
                </tone>
                <tone begin="81.811" end="82.216" lang="1" pitch="190" pronounce="">
                    <word>等</word>
                </tone>
                <tone begin="82.216" end="82.721" lang="1" pitch="273" pronounce="">
                    <word>待</word>
                </tone>
                <tone begin="82.721" end="83.176" lang="1" pitch="263" pronounce="">
                    <word>还</word>
                </tone>
                <tone begin="83.176" end="83.682" lang="1" pitch="222" pronounce="">
                    <word>是</word>
                </tone>
                <tone begin="83.682" end="84.086" lang="1" pitch="197" pronounce="">
                    <word>离</word>
                </tone>
                <tone begin="84.086" end="85.049" lang="1" pitch="211" pronounce="">
                    <word>开</word>
                </tone>
            </sentence>
            <sentence>
                <tone begin="88.033" end="88.336" lang="1" pitch="237" pronounce="">
                    <word>刮</word>
                </tone>
                <tone begin="88.336" end="88.793" lang="1" pitch="222" pronounce="">
                    <word>风</word>
                </tone>
                <tone begin="88.793" end="89.301" lang="1" pitch="245" pronounce="">
                    <word>这</word>
                </tone>
                <tone begin="89.301" end="89.808" lang="1" pitch="236" pronounce="">
                    <word>天</word>
                </tone>
                <tone begin="90.162" end="90.467" lang="1" pitch="120" pronounce="">
                    <word>我</word>
                </tone>
                <tone begin="90.467" end="90.923" lang="1" pitch="93" pronounce="">
                    <word>试</word>
                </tone>
                <tone begin="90.923" end="91.328" lang="1" pitch="334" pronounce="">
                    <word>过</word>
                </tone>
                <tone begin="91.328" end="91.784" lang="1" pitch="224" pronounce="">
                    <word>握</word>
                </tone>
                <tone begin="91.784" end="92.291" lang="1" pitch="304" pronounce="">
                    <word>着</word>
                </tone>
                <tone begin="92.291" end="92.847" lang="1" pitch="178" pronounce="">
                    <word>你</word>
                </tone>
                <tone begin="92.847" end="93.253" lang="1" pitch="170" pronounce="">
                    <word>手</word>
                </tone>
            </sentence>
            <sentence>
                <tone begin="93.557" end="93.962" lang="1" pitch="190" pronounce="">
                    <word>但</word>
                </tone>
                <tone begin="93.962" end="94.467" lang="1" pitch="193" pronounce="">
                    <word>偏</word>
                </tone>
                <tone begin="94.467" end="95.026" lang="1" pitch="323" pronounce="">
                    <word>偏</word>
                </tone>
                <tone begin="95.38" end="95.734" lang="1" pitch="319" pronounce="">
                    <word>雨</word>
                </tone>
                <tone begin="95.734" end="96.293" lang="1" pitch="294" pronounce="">
                    <word>渐</word>
                </tone>
                <tone begin="96.293" end="96.7" lang="1" pitch="291" pronounce="">
                    <word>渐</word>
                </tone>
                <tone begin="97.104" end="97.459" lang="1" pitch="279" pronounce="">
                    <word>大</word>
                </tone>
                <tone begin="97.459" end="97.965" lang="1" pitch="271" pronounce="">
                    <word>到</word>
                </tone>
                <tone begin="97.965" end="98.422" lang="1" pitch="247" pronounce="">
                    <word>我</word>
                </tone>
                <tone begin="98.422" end="98.878" lang="1" pitch="245" pronounce="">
                    <word>看</word>
                </tone>
                <tone begin="98.878" end="99.333" lang="1" pitch="244" pronounce="">
                    <word>你</word>
                </tone>
                <tone begin="99.333" end="99.839" lang="1" pitch="253" pronounce="">
                    <word>不</word>
                </tone>
                <tone begin="99.839" end="100.498" lang="1" pitch="240" pronounce="">
                    <word>见</word>
                </tone>
            </sentence>
            <sentence>
                <tone begin="102.023" end="102.376" lang="1" pitch="228" pronounce="">
                    <word>还</word>
                </tone>
                <tone begin="102.376" end="102.731" lang="1" pitch="273" pronounce="">
                    <word>要</word>
                </tone>
                <tone begin="102.731" end="103.288" lang="1" pitch="289" pronounce="">
                    <word>多</word>
                </tone>
                <tone begin="103.288" end="103.692" lang="1" pitch="238" pronounce="">
                    <word>久</word>
                </tone>
                <tone begin="104.148" end="104.502" lang="1" pitch="254" pronounce="">
                    <word>我</word>
                </tone>
                <tone begin="104.502" end="104.958" lang="1" pitch="291" pronounce="">
                    <word>才</word>
                </tone>
                <tone begin="104.958" end="105.416" lang="1" pitch="349" pronounce="">
                    <word>能</word>
                </tone>
                <tone begin="105.416" end="105.922" lang="1" pitch="402" pronounce="">
                    <word>在</word>
                </tone>
                <tone begin="105.922" end="106.378" lang="1" pitch="384" pronounce="">
                    <word>你</word>
                </tone>
                <tone begin="106.378" end="106.834" lang="1" pitch="380" pronounce="">
                    <word>身</word>
                </tone>
                <tone begin="106.834" end="107.641" lang="1" pitch="390" pronounce="">
                    <word>边</word>
                </tone>
            </sentence>
            <sentence>
                <tone begin="108.554" end="108.858" lang="1" pitch="376" pronounce="">
                    <word>等</word>
                </tone>
                <tone begin="108.858" end="109.312" lang="1" pitch="369" pronounce="">
                    <word>到</word>
                </tone>
                <tone begin="109.312" end="109.818" lang="1" pitch="293" pronounce="">
                    <word>放</word>
                </tone>
                <tone begin="109.818" end="110.224" lang="1" pitch="291" pronounce="">
                    <word>晴</word>
                </tone>
                <tone begin="110.224" end="110.73" lang="1" pitch="312" pronounce="">
                    <word>的</word>
                </tone>
                <tone begin="110.73" end="111.185" lang="1" pitch="287" pronounce="">
                    <word>那</word>
                </tone>
                <tone begin="111.185" end="111.387" lang="1" pitch="265" pronounce="">
                    <word>天</word>
                </tone>
            </sentence>
            <sentence>
                <tone begin="111.638" end="111.991" lang="1" pitch="219" pronounce="">
                    <word>也</word>
                </tone>
                <tone begin="111.991" end="112.397" lang="1" pitch="246" pronounce="">
                    <word>许</word>
                </tone>
                <tone begin="112.397" end="112.853" lang="1" pitch="249" pronounce="">
                    <word>我</word>
                </tone>
                <tone begin="112.853" end="113.307" lang="1" pitch="286" pronounce="">
                    <word>会</word>
                </tone>
                <tone begin="113.307" end="113.766" lang="1" pitch="298" pronounce="">
                    <word>比</word>
                </tone>
                <tone begin="113.766" end="114.271" lang="1" pitch="283" pronounce="">
                    <word>较</word>
                </tone>
                <tone begin="114.271" end="115.03" lang="1" pitch="345" pronounce="">
                    <word>好</word>
                </tone>
                <tone begin="115.03" end="115.181" lang="1" pitch="369" pronounce="">
                    <word>一</word>
                </tone>
                <tone begin="115.181" end="115.586" lang="1" pitch="360" pronounce="">
                    <word>点</word>
                </tone>
            </sentence>
            <sentence>
                <tone begin="115.991" end="116.344" lang="1" pitch="236" pronounce="">
                    <word>从</word>
                </tone>
                <tone begin="116.344" end="116.799" lang="1" pitch="224" pronounce="">
                    <word>前</word>
                </tone>
                <tone begin="116.799" end="117.353" lang="1" pitch="247" pronounce="">
                    <word>从</word>
                </tone>
                <tone begin="117.353" end="117.757" lang="1" pitch="246" pronounce="">
                    <word>前</word>
                </tone>
                <tone begin="118.112" end="118.518" lang="1" pitch="121" pronounce="">
                    <word>有</word>
                </tone>
                <tone begin="118.518" end="118.924" lang="1" pitch="94" pronounce="">
                    <word>个</word>
                </tone>
                <tone begin="118.924" end="119.38" lang="1" pitch="198" pronounce="">
                    <word>人</word>
                </tone>
                <tone begin="119.38" end="119.836" lang="1" pitch="232" pronounce="">
                    <word>爱</word>
                </tone>
                <tone begin="119.836" end="120.292" lang="1" pitch="337" pronounce="">
                    <word>你</word>
                </tone>
                <tone begin="120.292" end="120.897" lang="1" pitch="162" pronounce="">
                    <word>很</word>
                </tone>
                <tone begin="120.897" end="121.2" lang="1" pitch="171" pronounce="">
                    <word>久</word>
                </tone>
            </sentence>
            <sentence>
                <tone begin="121.555" end="122.062" lang="1" pitch="191" pronounce="">
                    <word>但</word>
                </tone>
                <tone begin="122.062" end="122.568" lang="1" pitch="233" pronounce="">
                    <word>偏</word>
                </tone>
                <tone begin="122.568" end="122.922" lang="1" pitch="203" pronounce="">
                    <word>偏</word>
                </tone>
                <tone begin="123.328" end="123.682" lang="1" pitch="205" pronounce="">
                    <word>风</word>
                </tone>
                <tone begin="123.682" end="124.238" lang="1" pitch="293" pronounce="">
                    <word>渐</word>
                </tone>
                <tone begin="124.238" end="124.643" lang="1" pitch="285" pronounce="">
                    <word>渐</word>
                </tone>
                <tone begin="125.152" end="125.556" lang="1" pitch="256" pronounce="">
                    <word>把</word>
                </tone>
                <tone begin="125.556" end="125.96" lang="1" pitch="245" pronounce="">
                    <word>距</word>
                </tone>
                <tone begin="125.96" end="126.416" lang="1" pitch="244" pronounce="">
                    <word>离</word>
                </tone>
                <tone begin="126.416" end="126.872" lang="1" pitch="210" pronounce="">
                    <word>吹</word>
                </tone>
                <tone begin="126.872" end="127.329" lang="1" pitch="233" pronounce="">
                    <word>得</word>
                </tone>
                <tone begin="127.329" end="127.885" lang="1" pitch="238" pronounce="">
                    <word>好</word>
                </tone>
                <tone begin="127.885" end="128.594" lang="1" pitch="240" pronounce="">
                    <word>远</word>
                </tone>
            </sentence>
            <sentence>
                <tone begin="130.002" end="130.306" lang="1" pitch="227" pronounce="">
                    <word>好</word>
                </tone>
                <tone begin="130.306" end="130.762" lang="1" pitch="265" pronounce="">
                    <word>不</word>
                </tone>
                <tone begin="130.762" end="131.319" lang="1" pitch="288" pronounce="">
                    <word>容</word>
                </tone>
                <tone begin="131.319" end="131.724" lang="1" pitch="240" pronounce="">
                    <word>易</word>
                </tone>
                <tone begin="132.078" end="132.484" lang="1" pitch="283" pronounce="">
                    <word>又</word>
                </tone>
                <tone begin="132.484" end="132.889" lang="1" pitch="287" pronounce="">
                    <word>能</word>
                </tone>
                <tone begin="132.889" end="133.395" lang="1" pitch="341" pronounce="">
                    <word>再</word>
                </tone>
                <tone begin="133.395" end="133.9" lang="1" pitch="399" pronounce="">
                    <word>多</word>
                </tone>
                <tone begin="133.9" end="134.356" lang="1" pitch="386" pronounce="">
                    <word>爱</word>
                </tone>
                <tone begin="134.356" end="134.863" lang="1" pitch="376" pronounce="">
                    <word>一</word>
                </tone>
                <tone begin="134.863" end="135.673" lang="1" pitch="389" pronounce="">
                    <word>天</word>
                </tone>
            </sentence>
            <sentence>
                <tone begin="136.582" end="136.886" lang="1" pitch="373" pronounce="">
                    <word>但</word>
                </tone>
                <tone begin="136.886" end="137.34" lang="1" pitch="363" pronounce="">
                    <word>故</word>
                </tone>
                <tone begin="137.34" end="137.794" lang="1" pitch="294" pronounce="">
                    <word>事</word>
                </tone>
                <tone begin="137.794" end="138.251" lang="1" pitch="285" pronounce="">
                    <word>的</word>
                </tone>
                <tone begin="138.251" end="138.705" lang="1" pitch="305" pronounce="">
                    <word>最</word>
                </tone>
                <tone begin="138.705" end="139.162" lang="1" pitch="282" pronounce="">
                    <word>后</word>
                </tone>
                <tone begin="139.162" end="139.616" lang="1" pitch="273" pronounce="">
                    <word>你</word>
                </tone>
                <tone begin="139.616" end="140.021" lang="1" pitch="145" pronounce="">
                    <word>好</word>
                </tone>
                <tone begin="140.021" end="140.426" lang="1" pitch="187" pronounce="">
                    <word>像</word>
                </tone>
                <tone begin="140.426" end="140.882" lang="1" pitch="201" pronounce="">
                    <word>还</word>
                </tone>
                <tone begin="140.882" end="141.337" lang="1" pitch="221" pronounce="">
                    <word>是</word>
                </tone>
                <tone begin="141.337" end="141.895" lang="1" pitch="231" pronounce="">
                    <word>说</word>
                </tone>
                <tone begin="141.895" end="142.3" lang="1" pitch="217" pronounce="">
                    <word>了</word>
                </tone>
            </sentence>
            <sentence>
                <tone begin="143.109" end="143.665" lang="1" pitch="219" pronounce="">
                    <word>拜</word>
                </tone>
                <tone begin="143.665" end="144.221" lang="1" pitch="193" pronounce="">
                    <word>拜</word>
                </tone>
            </sentence>
            <sentence>
                <tone begin="158.068" end="158.221" lang="1" pitch="191" pronounce="">
                    <word>为</word>
                </tone>
                <tone begin="158.221" end="158.372" lang="1" pitch="194" pronounce="">
                    <word>你</word>
                </tone>
                <tone begin="158.372" end="158.574" lang="1" pitch="193" pronounce="">
                    <word>翘</word>
                </tone>
                <tone begin="158.574" end="158.726" lang="1" pitch="193" pronounce="">
                    <word>课</word>
                </tone>
                <tone begin="158.726" end="158.928" lang="1" pitch="195" pronounce="">
                    <word>的</word>
                </tone>
                <tone begin="158.928" end="159.295" lang="1" pitch="203" pronounce="">
                    <word>那</word>
                </tone>
                <tone begin="159.295" end="159.648" lang="1" pitch="230" pronounce="">
                    <word>一</word>
                </tone>
                <tone begin="159.648" end="159.85" lang="1" pitch="195" pronounce="">
                    <word>天</word>
                </tone>
            </sentence>
            <sentence>
                <tone begin="160.002" end="160.205" lang="1" pitch="197" pronounce="">
                    <word>花</word>
                </tone>
                <tone begin="160.205" end="160.46" lang="1" pitch="194" pronounce="">
                    <word>落</word>
                </tone>
                <tone begin="160.46" end="160.663" lang="1" pitch="193" pronounce="">
                    <word>的</word>
                </tone>
                <tone begin="160.663" end="160.966" lang="1" pitch="162" pronounce="">
                    <word>那</word>
                </tone>
                <tone begin="160.966" end="161.322" lang="1" pitch="153" pronounce="">
                    <word>一</word>
                </tone>
                <tone begin="161.322" end="161.474" lang="1" pitch="137" pronounce="">
                    <word>天</word>
                </tone>
            </sentence>
            <sentence>
                <tone begin="161.778" end="161.98" lang="1" pitch="197" pronounce="">
                    <word>教</word>
                </tone>
                <tone begin="161.98" end="162.131" lang="1" pitch="193" pronounce="">
                    <word>室</word>
                </tone>
                <tone begin="162.131" end="162.386" lang="1" pitch="194" pronounce="">
                    <word>的</word>
                </tone>
                <tone begin="162.386" end="162.689" lang="1" pitch="213" pronounce="">
                    <word>那</word>
                </tone>
                <tone begin="162.689" end="163.094" lang="1" pitch="135" pronounce="">
                    <word>一</word>
                </tone>
                <tone begin="163.094" end="163.195" lang="1" pitch="98" pronounce="">
                    <word>间</word>
                </tone>
            </sentence>
            <sentence>
                <tone begin="163.498" end="163.701" lang="1" pitch="102" pronounce="">
                    <word>我</word>
                </tone>
                <tone begin="163.701" end="163.903" lang="1" pitch="103" pronounce="">
                    <word>怎</word>
                </tone>
                <tone begin="163.903" end="164.156" lang="1" pitch="129" pronounce="">
                    <word>么</word>
                </tone>
                <tone begin="164.156" end="164.461" lang="1" pitch="94" pronounce="">
                    <word>看</word>
                </tone>
                <tone begin="164.461" end="164.867" lang="1" pitch="97" pronounce="">
                    <word>不</word>
                </tone>
                <tone begin="164.867" end="165.02" lang="1" pitch="97" pronounce="">
                    <word>见</word>
                </tone>
            </sentence>
            <sentence>
                <tone begin="165.272" end="165.475" lang="1" pitch="232" pronounce="">
                    <word>消</word>
                </tone>
                <tone begin="165.475" end="165.677" lang="1" pitch="97" pronounce="">
                    <word>失</word>
                </tone>
                <tone begin="165.677" end="165.879" lang="1" pitch="171" pronounce="">
                    <word>的</word>
                </tone>
                <tone begin="165.879" end="166.184" lang="1" pitch="119" pronounce="">
                    <word>下</word>
                </tone>
                <tone begin="166.184" end="166.538" lang="1" pitch="105" pronounce="">
                    <word>雨</word>
                </tone>
                <tone begin="166.538" end="166.69" lang="1" pitch="296" pronounce="">
                    <word>天</word>
                </tone>
            </sentence>
            <sentence>
                <tone begin="167.045" end="167.247" lang="1" pitch="134" pronounce="">
                    <word>我</word>
                </tone>
                <tone begin="167.247" end="167.449" lang="1" pitch="251" pronounce="">
                    <word>好</word>
                </tone>
                <tone begin="167.449" end="167.701" lang="1" pitch="303" pronounce="">
                    <word>想</word>
                </tone>
                <tone begin="167.701" end="167.954" lang="1" pitch="280" pronounce="">
                    <word>再</word>
                </tone>
                <tone begin="167.954" end="168.207" lang="1" pitch="260" pronounce="">
                    <word>淋</word>
                </tone>
                <tone begin="168.207" end="168.41" lang="1" pitch="239" pronounce="">
                    <word>一</word>
                </tone>
                <tone begin="168.41" end="169.17" lang="1" pitch="195" pronounce="">
                    <word>遍</word>
                </tone>
            </sentence>
            <sentence>
                <tone begin="171.147" end="171.347" lang="1" pitch="195" pronounce="">
                    <word>没</word>
                </tone>
                <tone begin="171.347" end="171.501" lang="1" pitch="192" pronounce="">
                    <word>想</word>
                </tone>
                <tone begin="171.501" end="171.855" lang="1" pitch="186" pronounce="">
                    <word>到</word>
                </tone>
                <tone begin="171.855" end="172.108" lang="1" pitch="184" pronounce="">
                    <word>失</word>
                </tone>
                <tone begin="172.108" end="172.464" lang="1" pitch="162" pronounce="">
                    <word>去</word>
                </tone>
                <tone begin="172.464" end="172.867" lang="1" pitch="186" pronounce="">
                    <word>的</word>
                </tone>
                <tone begin="172.867" end="173.323" lang="1" pitch="191" pronounce="">
                    <word>勇</word>
                </tone>
                <tone begin="173.323" end="173.78" lang="1" pitch="282" pronounce="">
                    <word>气</word>
                </tone>
                <tone begin="173.78" end="174.236" lang="1" pitch="246" pronounce="">
                    <word>我</word>
                </tone>
                <tone begin="174.236" end="174.692" lang="1" pitch="235" pronounce="">
                    <word>还</word>
                </tone>
                <tone begin="174.692" end="175.147" lang="1" pitch="194" pronounce="">
                    <word>留</word>
                </tone>
                <tone begin="175.147" end="175.855" lang="1" pitch="194" pronounce="">
                    <word>着</word>
                </tone>
            </sentence>
            <sentence>
                <tone begin="177.295" end="177.546" lang="1" pitch="201" pronounce="">
                    <word>好</word>
                </tone>
                <tone begin="177.546" end="177.749" lang="1" pitch="185" pronounce="">
                    <word>想</word>
                </tone>
                <tone begin="177.749" end="177.951" lang="1" pitch="196" pronounce="">
                    <word>再</word>
                </tone>
                <tone begin="177.951" end="178.203" lang="1" pitch="130" pronounce="">
                    <word>问</word>
                </tone>
                <tone begin="178.203" end="178.509" lang="1" pitch="210" pronounce="">
                    <word>一</word>
                </tone>
                <tone begin="178.509" end="178.712" lang="1" pitch="182" pronounce="">
                    <word>遍</word>
                </tone>
            </sentence>
            <sentence>
                <tone begin="179.014" end="179.371" lang="1" pitch="168" pronounce="">
                    <word>你</word>
                </tone>
                <tone begin="179.371" end="179.776" lang="1" pitch="178" pronounce="">
                    <word>会</word>
                </tone>
                <tone begin="179.776" end="180.231" lang="1" pitch="190" pronounce="">
                    <word>等</word>
                </tone>
                <tone begin="180.231" end="180.689" lang="1" pitch="246" pronounce="">
                    <word>待</word>
                </tone>
                <tone begin="180.689" end="181.195" lang="1" pitch="220" pronounce="">
                    <word>还</word>
                </tone>
                <tone begin="181.195" end="181.649" lang="1" pitch="229" pronounce="">
                    <word>是</word>
                </tone>
                <tone begin="181.649" end="182.105" lang="1" pitch="192" pronounce="">
                    <word>离</word>
                </tone>
                <tone begin="182.105" end="182.911" lang="1" pitch="217" pronounce="">
                    <word>开</word>
                </tone>
            </sentence>
            <sentence>
                <tone begin="185.957" end="186.361" lang="1" pitch="235" pronounce="">
                    <word>刮</word>
                </tone>
                <tone begin="186.361" end="186.766" lang="1" pitch="225" pronounce="">
                    <word>风</word>
                </tone>
                <tone begin="186.766" end="187.37" lang="1" pitch="243" pronounce="">
                    <word>这</word>
                </tone>
                <tone begin="187.37" end="187.724" lang="1" pitch="248" pronounce="">
                    <word>天</word>
                </tone>
                <tone begin="188.076" end="188.483" lang="1" pitch="165" pronounce="">
                    <word>我</word>
                </tone>
                <tone begin="188.483" end="188.938" lang="1" pitch="121" pronounce="">
                    <word>试</word>
                </tone>
                <tone begin="188.938" end="189.392" lang="1" pitch="319" pronounce="">
                    <word>过</word>
                </tone>
                <tone begin="189.392" end="189.898" lang="1" pitch="215" pronounce="">
                    <word>握</word>
                </tone>
                <tone begin="189.898" end="190.303" lang="1" pitch="376" pronounce="">
                    <word>着</word>
                </tone>
                <tone begin="190.303" end="190.858" lang="1" pitch="200" pronounce="">
                    <word>你</word>
                </tone>
                <tone begin="190.858" end="191.163" lang="1" pitch="192" pronounce="">
                    <word>手</word>
                </tone>
            </sentence>
            <sentence>
                <tone begin="191.518" end="191.973" lang="1" pitch="188" pronounce="">
                    <word>但</word>
                </tone>
                <tone begin="191.973" end="192.531" lang="1" pitch="249" pronounce="">
                    <word>偏</word>
                </tone>
                <tone begin="192.531" end="192.935" lang="1" pitch="202" pronounce="">
                    <word>偏</word>
                </tone>
                <tone begin="193.391" end="193.695" lang="1" pitch="323" pronounce="">
                    <word>雨</word>
                </tone>
                <tone begin="193.695" end="194.301" lang="1" pitch="302" pronounce="">
                    <word>渐</word>
                </tone>
                <tone begin="194.301" end="194.604" lang="1" pitch="232" pronounce="">
                    <word>渐</word>
                </tone>
                <tone begin="195.057" end="195.511" lang="1" pitch="246" pronounce="">
                    <word>大</word>
                </tone>
                <tone begin="195.511" end="196.016" lang="1" pitch="273" pronounce="">
                    <word>到</word>
                </tone>
                <tone begin="196.016" end="196.472" lang="1" pitch="247" pronounce="">
                    <word>我</word>
                </tone>
                <tone begin="196.472" end="196.926" lang="1" pitch="214" pronounce="">
                    <word>看</word>
                </tone>
                <tone begin="196.926" end="197.33" lang="1" pitch="243" pronounce="">
                    <word>你</word>
                </tone>
                <tone begin="197.33" end="197.838" lang="1" pitch="249" pronounce="">
                    <word>不</word>
                </tone>
                <tone begin="197.838" end="198.545" lang="1" pitch="239" pronounce="">
                    <word>见</word>
                </tone>
            </sentence>
            <sentence>
                <tone begin="200.062" end="200.314" lang="1" pitch="219" pronounce="">
                    <word>还</word>
                </tone>
                <tone begin="200.314" end="200.821" lang="1" pitch="263" pronounce="">
                    <word>要</word>
                </tone>
                <tone begin="200.821" end="201.325" lang="1" pitch="294" pronounce="">
                    <word>多</word>
                </tone>
                <tone begin="201.325" end="201.73" lang="1" pitch="254" pronounce="">
                    <word>久</word>
                </tone>
                <tone begin="202.133" end="202.487" lang="1" pitch="276" pronounce="">
                    <word>我</word>
                </tone>
                <tone begin="202.487" end="203.042" lang="1" pitch="285" pronounce="">
                    <word>才</word>
                </tone>
                <tone begin="203.042" end="203.497" lang="1" pitch="349" pronounce="">
                    <word>能</word>
                </tone>
                <tone begin="203.497" end="204.003" lang="1" pitch="396" pronounce="">
                    <word>在</word>
                </tone>
                <tone begin="204.003" end="204.41" lang="1" pitch="389" pronounce="">
                    <word>你</word>
                </tone>
                <tone begin="204.41" end="204.917" lang="1" pitch="379" pronounce="">
                    <word>身</word>
                </tone>
                <tone begin="204.917" end="205.829" lang="1" pitch="217" pronounce="">
                    <word>边</word>
                </tone>
            </sentence>
            <sentence>
                <tone begin="206.535" end="206.887" lang="1" pitch="347" pronounce="">
                    <word>等</word>
                </tone>
                <tone begin="206.887" end="207.394" lang="1" pitch="374" pronounce="">
                    <word>到</word>
                </tone>
                <tone begin="207.394" end="207.951" lang="1" pitch="292" pronounce="">
                    <word>放</word>
                </tone>
                <tone begin="207.951" end="208.406" lang="1" pitch="293" pronounce="">
                    <word>晴</word>
                </tone>
                <tone begin="208.406" end="208.863" lang="1" pitch="317" pronounce="">
                    <word>的</word>
                </tone>
                <tone begin="208.863" end="209.267" lang="1" pitch="283" pronounce="">
                    <word>那</word>
                </tone>
                <tone begin="209.267" end="209.421" lang="1" pitch="269" pronounce="">
                    <word>天</word>
                </tone>
            </sentence>
            <sentence>
                <tone begin="209.674" end="210.079" lang="1" pitch="203" pronounce="">
                    <word>也</word>
                </tone>
                <tone begin="210.079" end="210.539" lang="1" pitch="243" pronounce="">
                    <word>许</word>
                </tone>
                <tone begin="210.539" end="210.998" lang="1" pitch="246" pronounce="">
                    <word>我</word>
                </tone>
                <tone begin="210.998" end="211.401" lang="1" pitch="275" pronounce="">
                    <word>会</word>
                </tone>
                <tone begin="211.401" end="211.856" lang="1" pitch="300" pronounce="">
                    <word>比</word>
                </tone>
                <tone begin="211.856" end="212.363" lang="1" pitch="277" pronounce="">
                    <word>较</word>
                </tone>
                <tone begin="212.363" end="213.071" lang="1" pitch="345" pronounce="">
                    <word>好</word>
                </tone>
                <tone begin="213.071" end="213.274" lang="1" pitch="368" pronounce="">
                    <word>一</word>
                </tone>
                <tone begin="213.274" end="213.679" lang="1" pitch="350" pronounce="">
                    <word>点</word>
                </tone>
            </sentence>
            <sentence>
                <tone begin="213.983" end="214.442" lang="1" pitch="239" pronounce="">
                    <word>从</word>
                </tone>
                <tone begin="214.442" end="214.895" lang="1" pitch="223" pronounce="">
                    <word>前</word>
                </tone>
                <tone begin="214.895" end="215.352" lang="1" pitch="244" pronounce="">
                    <word>从</word>
                </tone>
                <tone begin="215.352" end="215.806" lang="1" pitch="240" pronounce="">
                    <word>前</word>
                </tone>
                <tone begin="216.211" end="216.566" lang="1" pitch="192" pronounce="">
                    <word>有</word>
                </tone>
                <tone begin="216.566" end="217.071" lang="1" pitch="237" pronounce="">
                    <word>个</word>
                </tone>
                <tone begin="217.071" end="217.479" lang="1" pitch="363" pronounce="">
                    <word>人</word>
                </tone>
                <tone begin="217.479" end="217.985" lang="1" pitch="179" pronounce="">
                    <word>爱</word>
                </tone>
                <tone begin="217.985" end="218.391" lang="1" pitch="160" pronounce="">
                    <word>你</word>
                </tone>
                <tone begin="218.391" end="218.895" lang="1" pitch="420" pronounce="">
                    <word>很</word>
                </tone>
                <tone begin="218.895" end="219.703" lang="1" pitch="412" pronounce="">
                    <word>久</word>
                </tone>
            </sentence>
            <sentence>
                <tone begin="220.22" end="220.573" lang="1" pitch="378" pronounce="">
                    <word>偏</word>
                </tone>
                <tone begin="220.573" end="221.128" lang="1" pitch="315" pronounce="">
                    <word>偏</word>
                </tone>
                <tone begin="221.533" end="221.837" lang="1" pitch="310" pronounce="">
                    <word>风</word>
                </tone>
                <tone begin="221.837" end="222.344" lang="1" pitch="298" pronounce="">
                    <word>渐</word>
                </tone>
                <tone begin="222.344" end="222.699" lang="1" pitch="291" pronounce="">
                    <word>渐</word>
                </tone>
                <tone begin="223.155" end="223.509" lang="1" pitch="257" pronounce="">
                    <word>把</word>
                </tone>
                <tone begin="223.509" end="224.065" lang="1" pitch="262" pronounce="">
                    <word>距</word>
                </tone>
                <tone begin="224.065" end="224.419" lang="1" pitch="245" pronounce="">
                    <word>离</word>
                </tone>
                <tone begin="224.419" end="224.924" lang="1" pitch="256" pronounce="">
                    <word>吹</word>
                </tone>
                <tone begin="224.924" end="225.432" lang="1" pitch="224" pronounce="">
                    <word>得</word>
                </tone>
                <tone begin="225.432" end="225.989" lang="1" pitch="248" pronounce="">
                    <word>好</word>
                </tone>
                <tone begin="225.989" end="226.646" lang="1" pitch="238" pronounce="">
                    <word>远</word>
                </tone>
            </sentence>
            <sentence>
                <tone begin="227.991" end="228.449" lang="1" pitch="232" pronounce="">
                    <word>好</word>
                </tone>
                <tone begin="228.449" end="228.855" lang="1" pitch="268" pronounce="">
                    <word>不</word>
                </tone>
                <tone begin="228.855" end="229.36" lang="1" pitch="294" pronounce="">
                    <word>容</word>
                </tone>
                <tone begin="229.36" end="229.764" lang="1" pitch="249" pronounce="">
                    <word>易</word>
                </tone>
                <tone begin="230.169" end="230.575" lang="1" pitch="298" pronounce="">
                    <word>又</word>
                </tone>
                <tone begin="230.575" end="231.032" lang="1" pitch="293" pronounce="">
                    <word>能</word>
                </tone>
                <tone begin="231.032" end="231.486" lang="1" pitch="348" pronounce="">
                    <word>再</word>
                </tone>
                <tone begin="231.486" end="231.994" lang="1" pitch="408" pronounce="">
                    <word>多</word>
                </tone>
                <tone begin="231.994" end="232.449" lang="1" pitch="379" pronounce="">
                    <word>爱</word>
                </tone>
                <tone begin="232.449" end="232.955" lang="1" pitch="379" pronounce="">
                    <word>一</word>
                </tone>
                <tone begin="232.955" end="233.816" lang="1" pitch="388" pronounce="">
                    <word>天</word>
                </tone>
            </sentence>
            <sentence>
                <tone begin="234.627" end="235.032" lang="1" pitch="365" pronounce="">
                    <word>但</word>
                </tone>
                <tone begin="235.032" end="235.486" lang="1" pitch="354" pronounce="">
                    <word>故</word>
                </tone>
                <tone begin="235.486" end="235.892" lang="1" pitch="289" pronounce="">
                    <word>事</word>
                </tone>
                <tone begin="235.892" end="236.295" lang="1" pitch="290" pronounce="">
                    <word>的</word>
                </tone>
                <tone begin="236.295" end="236.802" lang="1" pitch="320" pronounce="">
                    <word>最</word>
                </tone>
                <tone begin="236.802" end="237.257" lang="1" pitch="286" pronounce="">
                    <word>后</word>
                </tone>
                <tone begin="237.257" end="237.662" lang="1" pitch="269" pronounce="">
                    <word>你</word>
                </tone>
                <tone begin="237.662" end="238.066" lang="1" pitch="164" pronounce="">
                    <word>好</word>
                </tone>
                <tone begin="238.066" end="238.524" lang="1" pitch="183" pronounce="">
                    <word>像</word>
                </tone>
                <tone begin="238.524" end="238.978" lang="1" pitch="184" pronounce="">
                    <word>还</word>
                </tone>
                <tone begin="238.978" end="239.436" lang="1" pitch="218" pronounce="">
                    <word>是</word>
                </tone>
                <tone begin="239.436" end="240.144" lang="1" pitch="226" pronounce="">
                    <word>说</word>
                </tone>
                <tone begin="240.144" end="240.496" lang="1" pitch="217" pronounce="">
                    <word>了</word>
                </tone>
            </sentence>
            <sentence>
                <tone begin="241.22" end="241.625" lang="1" pitch="199" pronounce="">
                    <word>拜</word>
                </tone>
                <tone begin="241.625" end="241.827" lang="1" pitch="134" pronounce="">
                    <word>拜</word>
                </tone>
                <tone begin="241.827" end="241.979" lang="1" pitch="216" pronounce="">
                    <word>刮</word>
                </tone>
                <tone begin="241.979" end="242.08" lang="1" pitch="190" pronounce="">
                    <word>风</word>
                </tone>
                <tone begin="242.08" end="242.424" lang="1" pitch="195" pronounce="">
                    <word>这</word>
                </tone>
                <tone begin="242.424" end="242.779" lang="1" pitch="191" pronounce="">
                    <word>天</word>
                </tone>
                <tone begin="242.779" end="243.082" lang="1" pitch="195" pronounce="">
                    <word>我</word>
                </tone>
                <tone begin="243.082" end="243.285" lang="1" pitch="194" pronounce="">
                    <word>试</word>
                </tone>
                <tone begin="243.285" end="243.74" lang="1" pitch="183" pronounce="">
                    <word>过</word>
                </tone>
                <tone begin="243.74" end="244.198" lang="1" pitch="190" pronounce="">
                    <word>握</word>
                </tone>
                <tone begin="244.198" end="244.399" lang="1" pitch="184" pronounce="">
                    <word>着</word>
                </tone>
                <tone begin="244.399" end="244.602" lang="1" pitch="193" pronounce="">
                    <word>你</word>
                </tone>
                <tone begin="244.602" end="244.856" lang="1" pitch="191" pronounce="">
                    <word>手</word>
                </tone>
            </sentence>
            <sentence>
                <tone begin="245.112" end="245.313" lang="1" pitch="191" pronounce="">
                    <word>但</word>
                </tone>
                <tone begin="245.313" end="245.467" lang="1" pitch="193" pronounce="">
                    <word>偏</word>
                </tone>
                <tone begin="245.467" end="245.972" lang="1" pitch="188" pronounce="">
                    <word>偏</word>
                </tone>
                <tone begin="245.972" end="246.175" lang="1" pitch="191" pronounce="">
                    <word>雨</word>
                </tone>
                <tone begin="246.175" end="246.328" lang="1" pitch="184" pronounce="">
                    <word>渐</word>
                </tone>
                <tone begin="246.328" end="246.784" lang="1" pitch="192" pronounce="">
                    <word>渐</word>
                </tone>
                <tone begin="246.784" end="246.987" lang="1" pitch="192" pronounce="">
                    <word>大</word>
                </tone>
                <tone begin="246.987" end="247.19" lang="1" pitch="185" pronounce="">
                    <word>到</word>
                </tone>
                <tone begin="247.19" end="247.391" lang="1" pitch="179" pronounce="">
                    <word>我</word>
                </tone>
                <tone begin="247.391" end="247.594" lang="1" pitch="187" pronounce="">
                    <word>看</word>
                </tone>
                <tone begin="247.594" end="247.797" lang="1" pitch="176" pronounce="">
                    <word>你</word>
                </tone>
                <tone begin="247.797" end="248.049" lang="1" pitch="172" pronounce="">
                    <word>不</word>
                </tone>
                <tone begin="248.049" end="248.2" lang="1" pitch="195" pronounce="">
                    <word>见</word>
                </tone>
            </sentence>
            <sentence>
                <tone begin="248.715" end="248.917" lang="1" pitch="196" pronounce="">
                    <word>还</word>
                </tone>
                <tone begin="248.917" end="249.172" lang="1" pitch="193" pronounce="">
                    <word>要</word>
                </tone>
                <tone begin="249.172" end="249.527" lang="1" pitch="192" pronounce="">
                    <word>多</word>
                </tone>
                <tone begin="249.527" end="249.982" lang="1" pitch="176" pronounce="">
                    <word>久</word>
                </tone>
                <tone begin="249.982" end="250.236" lang="1" pitch="180" pronounce="">
                    <word>我</word>
                </tone>
                <tone begin="250.236" end="250.438" lang="1" pitch="184" pronounce="">
                    <word>才</word>
                </tone>
                <tone begin="250.438" end="250.69" lang="1" pitch="190" pronounce="">
                    <word>能</word>
                </tone>
                <tone begin="250.69" end="250.944" lang="1" pitch="193" pronounce="">
                    <word>够</word>
                </tone>
                <tone begin="250.944" end="251.095" lang="1" pitch="183" pronounce="">
                    <word>在</word>
                </tone>
                <tone begin="251.095" end="251.348" lang="1" pitch="187" pronounce="">
                    <word>你</word>
                </tone>
                <tone begin="251.348" end="251.549" lang="1" pitch="188" pronounce="">
                    <word>身</word>
                </tone>
                <tone begin="251.549" end="251.702" lang="1" pitch="194" pronounce="">
                    <word>边</word>
                </tone>
            </sentence>
            <sentence>
                <tone begin="252.158" end="252.413" lang="1" pitch="190" pronounce="">
                    <word>等</word>
                </tone>
                <tone begin="252.413" end="252.614" lang="1" pitch="97" pronounce="">
                    <word>到</word>
                </tone>
                <tone begin="252.614" end="252.816" lang="1" pitch="155" pronounce="">
                    <word>放</word>
                </tone>
                <tone begin="252.816" end="253.071" lang="1" pitch="191" pronounce="">
                    <word>晴</word>
                </tone>
                <tone begin="253.071" end="253.325" lang="1" pitch="191" pronounce="">
                    <word>那</word>
                </tone>
                <tone begin="253.325" end="253.426" lang="1" pitch="199" pronounce="">
                    <word>天</word>
                </tone>
            </sentence>
            <sentence>
                <tone begin="253.78" end="254.034" lang="1" pitch="145" pronounce="">
                    <word>也</word>
                </tone>
                <tone begin="254.034" end="254.237" lang="1" pitch="185" pronounce="">
                    <word>许</word>
                </tone>
                <tone begin="254.237" end="254.44" lang="1" pitch="194" pronounce="">
                    <word>我</word>
                </tone>
                <tone begin="254.44" end="254.694" lang="1" pitch="188" pronounce="">
                    <word>会</word>
                </tone>
                <tone begin="254.694" end="254.846" lang="1" pitch="193" pronounce="">
                    <word>比</word>
                </tone>
                <tone begin="254.846" end="255.1" lang="1" pitch="191" pronounce="">
                    <word>较</word>
                </tone>
                <tone begin="255.1" end="255.373" lang="1" pitch="194" pronounce="">
                    <word>好</word>
                </tone>
                <tone begin="255.373" end="255.672" lang="1" pitch="184" pronounce="">
                    <word>一</word>
                </tone>
                <tone begin="255.672" end="255.824" lang="1" pitch="171" pronounce="">
                    <word>点</word>
                </tone>
            </sentence>
            <sentence>
                <tone begin="255.976" end="256.129" lang="1" pitch="187" pronounce="">
                    <word>从</word>
                </tone>
                <tone begin="256.129" end="256.331" lang="1" pitch="193" pronounce="">
                    <word>前</word>
                </tone>
                <tone begin="256.331" end="256.633" lang="1" pitch="194" pronounce="">
                    <word>从</word>
                </tone>
                <tone begin="256.633" end="257.04" lang="1" pitch="197" pronounce="">
                    <word>前</word>
                </tone>
                <tone begin="257.04" end="257.293" lang="1" pitch="195" pronounce="">
                    <word>有</word>
                </tone>
                <tone begin="257.293" end="257.495" lang="1" pitch="185" pronounce="">
                    <word>个</word>
                </tone>
                <tone begin="257.495" end="257.898" lang="1" pitch="175" pronounce="">
                    <word>人</word>
                </tone>
                <tone begin="257.898" end="258.152" lang="1" pitch="185" pronounce="">
                    <word>爱</word>
                </tone>
                <tone begin="258.152" end="258.353" lang="1" pitch="179" pronounce="">
                    <word>你</word>
                </tone>
                <tone begin="258.353" end="258.555" lang="1" pitch="186" pronounce="">
                    <word>很</word>
                </tone>
                <tone begin="258.555" end="258.708" lang="1" pitch="184" pronounce="">
                    <word>久</word>
                </tone>
            </sentence>
            <sentence>
                <tone begin="259.012" end="259.214" lang="1" pitch="193" pronounce="">
                    <word>但</word>
                </tone>
                <tone begin="259.214" end="259.468" lang="1" pitch="197" pronounce="">
                    <word>偏</word>
                </tone>
                <tone begin="259.468" end="259.923" lang="1" pitch="191" pronounce="">
                    <word>偏</word>
                </tone>
                <tone begin="259.923" end="260.125" lang="1" pitch="187" pronounce="">
                    <word>雨</word>
                </tone>
                <tone begin="260.125" end="260.328" lang="1" pitch="187" pronounce="">
                    <word>渐</word>
                </tone>
                <tone begin="260.328" end="260.782" lang="1" pitch="188" pronounce="">
                    <word>渐</word>
                </tone>
                <tone begin="260.782" end="260.985" lang="1" pitch="0" pronounce="">
                    <word>把</word>
                </tone>
                <tone begin="260.985" end="261.19" lang="1" pitch="189" pronounce="">
                    <word>距</word>
                </tone>
                <tone begin="261.19" end="261.394" lang="1" pitch="185" pronounce="">
                    <word>离</word>
                </tone>
                <tone begin="261.394" end="261.765" lang="1" pitch="189" pronounce="">
                    <word>吹</word>
                </tone>
                <tone begin="261.765" end="261.967" lang="1" pitch="184" pronounce="">
                    <word>得</word>
                </tone>
                <tone begin="261.967" end="262.168" lang="1" pitch="190" pronounce="">
                    <word>好</word>
                </tone>
                <tone begin="262.168" end="262.372" lang="1" pitch="178" pronounce="">
                    <word>远</word>
                </tone>
            </sentence>
            <sentence>
                <tone begin="262.51" end="262.811" lang="1" pitch="194" pronounce="">
                    <word>好</word>
                </tone>
                <tone begin="262.811" end="263.132" lang="1" pitch="193" pronounce="">
                    <word>不</word>
                </tone>
                <tone begin="263.132" end="263.335" lang="1" pitch="200" pronounce="">
                    <word>容</word>
                </tone>
                <tone begin="263.335" end="263.586" lang="1" pitch="193" pronounce="">
                    <word>易</word>
                </tone>
                <tone begin="263.739" end="264.193" lang="1" pitch="175" pronounce="">
                    <word>又</word>
                </tone>
                <tone begin="264.193" end="264.495" lang="1" pitch="182" pronounce="">
                    <word>能</word>
                </tone>
                <tone begin="264.495" end="264.9" lang="1" pitch="151" pronounce="">
                    <word>再</word>
                </tone>
                <tone begin="264.9" end="265.205" lang="1" pitch="205" pronounce="">
                    <word>多</word>
                </tone>
                <tone begin="265.205" end="265.406" lang="1" pitch="121" pronounce="">
                    <word>爱</word>
                </tone>
                <tone begin="265.406" end="265.607" lang="1" pitch="207" pronounce="">
                    <word>一</word>
                </tone>
                <tone begin="265.607" end="265.759" lang="1" pitch="194" pronounce="">
                    <word>天</word>
                </tone>
            </sentence>
            <sentence>
                <tone begin="266.011" end="266.266" lang="1" pitch="101" pronounce="">
                    <word>但</word>
                </tone>
                <tone begin="266.266" end="266.47" lang="1" pitch="198" pronounce="">
                    <word>故</word>
                </tone>
                <tone begin="266.47" end="266.673" lang="1" pitch="192" pronounce="">
                    <word>事</word>
                </tone>
                <tone begin="266.673" end="266.883" lang="1" pitch="194" pronounce="">
                    <word>的</word>
                </tone>
                <tone begin="266.883" end="267.134" lang="1" pitch="194" pronounce="">
                    <word>最</word>
                </tone>
                <tone begin="267.134" end="267.337" lang="1" pitch="196" pronounce="">
                    <word>后</word>
                </tone>
                <tone begin="267.337" end="267.589" lang="1" pitch="195" pronounce="">
                    <word>你</word>
                </tone>
                <tone begin="267.589" end="267.791" lang="1" pitch="200" pronounce="">
                    <word>好</word>
                </tone>
                <tone begin="267.791" end="267.995" lang="1" pitch="192" pronounce="">
                    <word>像</word>
                </tone>
                <tone begin="267.995" end="268.25" lang="1" pitch="194" pronounce="">
                    <word>还</word>
                </tone>
                <tone begin="268.25" end="268.452" lang="1" pitch="196" pronounce="">
                    <word>是</word>
                </tone>
                <tone begin="268.452" end="268.653" lang="1" pitch="194" pronounce="">
                    <word>说</word>
                </tone>
                <tone begin="268.653" end="268.958" lang="1" pitch="194" pronounce="">
                    <word>了</word>
                </tone>
                <tone begin="268.958" end="269.364" lang="1" pitch="193" pronounce="">
                    <word>拜</word>
                </tone>
            </sentence>
        </paragraph>
    </midi_lrc>
</song>